CHANGES.txt
CONTRIBUTORS.txt
MANIFEST.in
README.txt
setup.cfg
setup.py
cs/__init__.py
cs.kontratazioa.egg-info/PKG-INFO
cs.kontratazioa.egg-info/SOURCES.txt
cs.kontratazioa.egg-info/dependency_links.txt
cs.kontratazioa.egg-info/entry_points.txt
cs.kontratazioa.egg-info/namespace_packages.txt
cs.kontratazioa.egg-info/not-zip-safe
cs.kontratazioa.egg-info/requires.txt
cs.kontratazioa.egg-info/top_level.txt
cs/kontratazioa/__init__.py
cs/kontratazioa/config.py
cs/kontratazioa/configure.zcml
cs/kontratazioa/rebuild_i18n.sh
cs/kontratazioa/browser/__init__.py
cs/kontratazioa/browser/configure.zcml
cs/kontratazioa/browser/kontratazioa_general.pt
cs/kontratazioa/browser/kontratazioa_list.py
cs/kontratazioa/browser/kontratazioafolderview.pt
cs/kontratazioa/browser/kontratazioafolderview.py
cs/kontratazioa/browser/kontratazioaview.pt
cs/kontratazioa/browser/kontratazioaview.py
cs/kontratazioa/browser/state_list.py
cs/kontratazioa/browser/css/cs.kontratazioa.css
cs/kontratazioa/content/__init__.py
cs/kontratazioa/content/configure.zcml
cs/kontratazioa/content/kontratazioa.py
cs/kontratazioa/content/kontratazioafolder.py
cs/kontratazioa/interfaces/__init__.py
cs/kontratazioa/interfaces/kontratazioa.py
cs/kontratazioa/interfaces/kontratazioafolder.py
cs/kontratazioa/locales/cs.kontratazioa-manual.pot
cs/kontratazioa/locales/cs.kontratazioa.pot
cs/kontratazioa/locales/plone.pot
cs/kontratazioa/locales/es/LC_MESSAGES/cs.kontratazioa.po
cs/kontratazioa/locales/es/LC_MESSAGES/plone.po
cs/kontratazioa/locales/eu/LC_MESSAGES/cs.kontratazioa.po
cs/kontratazioa/locales/eu/LC_MESSAGES/plone.po
cs/kontratazioa/profiles/default/catalog.xml
cs/kontratazioa/profiles/default/cssregistry.xml
cs/kontratazioa/profiles/default/factorytool.xml
cs/kontratazioa/profiles/default/metadata.xml
cs/kontratazioa/profiles/default/portlets.xml
cs/kontratazioa/profiles/default/propertiestool.xml
cs/kontratazioa/profiles/default/rolemap.xml
cs/kontratazioa/profiles/default/types.xml
cs/kontratazioa/profiles/default/types/kontratazioa.xml
cs/kontratazioa/profiles/default/types/kontratazioaFolder.xml
docs/HISTORY.txt
docs/INSTALL.txt
docs/LICENSE.GPL
docs/LICENSE.txt