Metadata-Version: 1.1
Name: cs.kontratazioa
Version: 2.2
Summary: A product to publish public contract information in Spanish Public Administration's websites
Home-page: http://github.com/codesyntax/cs.kontratazioa
Author: Lur Ibargutxi
Author-email: libargutxi@codesyntax.com
License: GPL
Platform: UNKNOWN
Classifier: Framework :: Plone
Classifier: Intended Audience :: Developers
Classifier: Topic :: Software Development :: Libraries :: Python Modules
Classifier: License :: OSI Approved :: GNU General Public License (GPL)
